{
  "_fv": 18,
  "_type": "recipe",
  "definition": {
    "recipeType": "Crafting",
    "xpReward": 0.0,
    "cookingTime": 200,
    "recipeRetstackSize": 1,
    "group": "",
    "recipeShapeless": false,
    "recipeSlots": [
      {
        "value": ""
      },
      {
        "value": "CUSTOM:Alexium"
      },
      {
        "value": "CUSTOM:PoweredAlexium"
      },
      {
        "value": "CUSTOM:AlexiumNugget"
      },
      {
        "value": "CUSTOM:IronRod"
      },
      {
        "value": "CUSTOM:Alexium"
      },
      {
        "value": "CUSTOM:IronRod"
      },
      {
        "value": "CUSTOM:AlexiumNugget"
      },
      {
        "value": ""
      }
    ],
    "recipeReturnStack": {
      "value": "CUSTOM:AlexitePickaxe"
    },
    "name": "craft_alick",
    "namespace": "mod"
  }
}