{
  "_fv": 18,
  "_type": "recipe",
  "definition": {
    "recipeType": "Crafting",
    "xpReward": 0.0,
    "cookingTime": 200,
    "recipeRetstackSize": 1,
    "group": "",
    "recipeShapeless": false,
    "recipeSlots": [
      {
        "value": ""
      },
      {
        "value": "CUSTOM:IronRod"
      },
      {
        "value": "Blocks.IRON_BLOCK"
      },
      {
        "value": "Blocks.IRON_TRAPDOOR"
      },
      {
        "value": "Blocks.IRON_BLOCK"
      },
      {
        "value": "CUSTOM:IronRod"
      },
      {
        "value": "Items.FLINT_AND_STEEL"
      },
      {
        "value": "Blocks.IRON_TRAPDOOR"
      },
      {
        "value": ""
      }
    ],
    "recipeReturnStack": {
      "value": "CUSTOM:UnpreppedShuttle"
    },
    "name": "make_unprepped_rocket",
    "namespace": "mod"
  }
}