{
  "_fv": 18,
  "_type": "recipe",
  "definition": {
    "recipeType": "Crafting",
    "xpReward": 0.0,
    "cookingTime": 200,
    "recipeRetstackSize": 1,
    "group": "",
    "recipeShapeless": false,
    "recipeSlots": [
      {
        "value": ""
      },
      {
        "value": ""
      },
      {
        "value": ""
      },
      {
        "value": "Blocks.PACKED_ICE"
      },
      {
        "value": "CUSTOM:AmongDrip"
      },
      {
        "value": "Items.BLAZE_POWDER"
      },
      {
        "value": ""
      },
      {
        "value": ""
      },
      {
        "value": ""
      }
    ],
    "recipeReturnStack": {
      "value": "CUSTOM:SusmeiserTheme"
    },
    "name": "makea_sussy_song",
    "namespace": "mod"
  }
}