{
  "_fv": 18,
  "_type": "dimension",
  "definition": {
    "biomesInDimension": [
      {
        "value": "CUSTOM:MossyHollows"
      }
    ],
    "worldGenType": "Nether like gen",
    "mainFillerBlock": {
      "value": "CUSTOM:Moss"
    },
    "fluidBlock": {
      "value": "Blocks.WATER"
    },
    "airColor": {
      "value": -11359675,
      "falpha": 0.0
    },
    "canRespawnHere": false,
    "hasFog": false,
    "isDark": false,
    "doesWaterVaporize": false,
    "sleepResult": "ALLOW",
    "hasSkyLight": false,
    "imitateOverworldBehaviour": false,
    "portalFrame": {
      "value": "Blocks.EMERALD_BLOCK"
    },
    "portalParticles": {
      "value": "WATER_BUBBLE"
    },
    "portalLuminance": 0,
    "portalSound": {
      "value": "block.portal.ambient"
    },
    "igniterName": "Wormhole Flute",
    "igniterTab": {
      "value": "CUSTOM:UnitedPlanets"
    },
    "texture": "staffpole",
    "portalTexture": "moss_block",
    "enablePortal": true,
    "whenPortaTriggerlUsed": {
      "name": "UnderblankarianZonePortalTriggerUsed"
    }
  }
}